pyze/__init__.py
pyze/api/__init__.py
pyze/api/credentials.py
pyze/api/gigya.py
pyze/api/kamereon.py
pyze/api/schedule.py
pyze/api/__tests__/__init__.py
pyze/api/__tests__/test_schedule.py
pyze/cli/__init__.py
pyze/cli/__main__.py
pyze/cli/ac-history.py
pyze/cli/ac-stats.py
pyze/cli/ac.py
pyze/cli/charge-history.py
pyze/cli/charge-mode.py
pyze/cli/charge-start.py
pyze/cli/charge-stats.py
pyze/cli/common.py
pyze/cli/login.py
pyze/cli/schedule.py
pyze/cli/set-account.py
pyze/cli/status.py
pyze/cli/vehicles.py
pyze/cli/__tests__/__init__.py
pyze/cli/__tests__/test_cli_schedule.py
PyZE-0.6.0.dist-info/LICENSE
PyZE-0.6.0.dist-info/METADATA
PyZE-0.6.0.dist-info/WHEEL
PyZE-0.6.0.dist-info/entry_points.txt
PyZE-0.6.0.dist-info/top_level.txt
PyZE-0.6.0.dist-info/RECORD
