Metadata-Version: 2.1
Name: PyZE
Version: 0.6.0
Summary: Unofficial client and API for Renault ZE
Home-page: https://github.com/jamesremuscat/pyze
Author: James Muscat
Author-email: jamesremuscat@gmail.com
License: UNKNOWN
Platform: UNKNOWN
Classifier: Programming Language :: Python :: 3
Classifier: License :: OSI Approved :: MIT License
Classifier: Operating System :: OS Independent
Requires-Dist: dateparser
Requires-Dist: pyjwt
Requires-Dist: python-dateutil
Requires-Dist: requests
Requires-Dist: simplejson
Requires-Dist: tabulate
Requires-Dist: tzlocal
